duck_orm/__init__.py
duck_orm/exceptions.py
duck_orm/model.py
duck_orm/model_manager.py
duck_orm/sql/__init__.py
duck_orm/sql/condition.py
duck_orm/sql/fields.py
duck_orm/sql/operator.py
duck_orm/sql/postgres/__init__.py
duck_orm/sql/relationship.py
duck_orm/sql/sql.py
duck_orm/sql/sqlite/__init__.py
duck_orm/utils/__init__.py
duck_orm/utils/functions.py
duck_orm-1.0.2.dist-info/LICENSE
duck_orm-1.0.2.dist-info/METADATA
duck_orm-1.0.2.dist-info/WHEEL
duck_orm-1.0.2.dist-info/RECORD
